templatekit/__init__.py
templatekit/builder.py
templatekit/configschema.yaml
templatekit/filerender.py
templatekit/jinjaext.py
templatekit/repo.py
templatekit/textutils.py
templatekit/scripts/__init__.py
templatekit/scripts/check.py
templatekit/scripts/listtemplates.py
templatekit/scripts/main.py
templatekit/scripts/make.py
templatekit-0.6.0.dist-info/LICENSE
templatekit-0.6.0.dist-info/METADATA
templatekit-0.6.0.dist-info/WHEEL
templatekit-0.6.0.dist-info/entry_points.txt
templatekit-0.6.0.dist-info/top_level.txt
templatekit-0.6.0.dist-info/RECORD
