Metadata-Version: 2.1
Name: templatekit
Version: 0.6.0
Summary: Tookit for rendering Rubin Observatory project templates
Author-email: "Association of Universities for Research in Astronomy, Inc. (AURA)" <sqre-admin@lists.lsst.org>, Jonathan Sick <jsick@lsst.org>
License: MIT License
Project-URL: Homepage, https://templatekit.lsst.io
Project-URL: Source, https://github.com/lsst-sqre/templatekit
Keywords: rubin,lsst
Classifier: Development Status :: 4 - Beta
Classifier: License :: OSI Approved :: MIT License
Classifier: Programming Language :: Python
Classifier: Programming Language :: Python :: 3
Classifier: Programming Language :: Python :: 3.8
Classifier: Programming Language :: Python :: 3.9
Classifier: Programming Language :: Python :: 3.10
Classifier: Programming Language :: Python :: 3.11
Classifier: Intended Audience :: Developers
Classifier: Natural Language :: English
Classifier: Operating System :: POSIX
Classifier: Typing :: Typed
Requires-Python: >=3.8
License-File: LICENSE
Requires-Dist: Cerberus >=1.2
Requires-Dist: click
Requires-Dist: cookiecutter >=1.6.0
Requires-Dist: GitPython >=3.0.0
Requires-Dist: Jinja2 >=2.10
Requires-Dist: pyperclip >=1.6.0
Requires-Dist: PyYAML >=5.1
Requires-Dist: scons >=3.0.1
Provides-Extra: dev
Requires-Dist: coverage[toml] ; extra == 'dev'
Requires-Dist: mypy ; extra == 'dev'
Requires-Dist: pre-commit ; extra == 'dev'
Requires-Dist: pytest ; extra == 'dev'
Requires-Dist: pytest-cov ; extra == 'dev'
Requires-Dist: types-PyYAML ; extra == 'dev'
Requires-Dist: documenteer[guide] ; extra == 'dev'
Requires-Dist: sphinx-click ; extra == 'dev'
